mcp_amplitude/__init__.py
mcp_amplitude/server.py
mcp_amplitude-0.0.2.dist-info/METADATA
mcp_amplitude-0.0.2.dist-info/WHEEL
mcp_amplitude-0.0.2.dist-info/entry_points.txt
mcp_amplitude-0.0.2.dist-info/top_level.txt
mcp_amplitude-0.0.2.dist-info/RECORD
