Metadata-Version: 2.4
Name: mcp-amplitude
Version: 0.0.2
Summary: MCP server for Amplitude integration
Project-URL: Homepage, https://github.com/your-username/mcp-amplitude
Project-URL: Bug Tracker, https://github.com/your-username/mcp-amplitude/issues
Requires-Python: >=3.10
Requires-Dist: mcp[cli]>=1.6.0
Requires-Dist: httpx>=0.24.0
